SerialLibrary/__init__.py
SerialLibrary/version.py
robotframework_seriallibrary-0.4.2.dist-info/LICENSE
robotframework_seriallibrary-0.4.2.dist-info/WHEEL
robotframework_seriallibrary-0.4.2.dist-info/METADATA
robotframework_seriallibrary-0.4.2.dist-info/RECORD
