Metadata-Version: 2.1
Name: robotframework-seriallibrary
Version: 0.4.2
Summary: Robot Framework test library for serial connection
Home-page: https://github.com/whosaysni/robotframework-seriallibrary/
License: Apache-2.0
Keywords: robotframework,testing,testautomation,serial
Author: Yasushi Masuda
Author-email: whosaysni@gmail.com
Classifier: Development Status :: 3 - Alpha
Classifier: License :: OSI Approved :: Apache Software License
Classifier: Operating System :: OS Independent
Classifier: Programming Language :: Python :: 2
Classifier: Programming Language :: Python :: 2.7
Classifier: Programming Language :: Python :: 3
Classifier: Programming Language :: Python :: 3.10
Classifier: Programming Language :: Python :: 3.4
Classifier: Programming Language :: Python :: 3.5
Classifier: Programming Language :: Python :: 3.6
Classifier: Programming Language :: Python :: 3.7
Classifier: Programming Language :: Python :: 3.8
Classifier: Programming Language :: Python :: 3.9
Classifier: Topic :: Software Development :: Testing
Requires-Dist: install_requires
Requires-Dist: install_requires
Project-URL: Repository, https://github.com/whosaysni/robotframework-seriallibrary/
